{
    "dialogue_id": 1539,
    "interlocutors": [
        "BA",
        "AK"
    ],
    "utterances": [
        {
            "utterance_id": 0,
            "interlocutor_id": "BA",
            "text": "こんにちは",
            "timestamp": "2022-08-15T12:11:37.320000"
        },
        {
            "utterance_id": 1,
            "interlocutor_id": "AK",
            "text": "こんにちはー！",
            "timestamp": "2022-08-15T12:11:41.526000"
        },
        {
            "utterance_id": 2,
            "interlocutor_id": "BA",
            "text": "機械に詳しいですか？",
            "timestamp": "2022-08-15T12:11:55.862000"
        },
        {
            "utterance_id": 3,
            "interlocutor_id": "AK",
            "text": "え、どんな機械ですか？",
            "timestamp": "2022-08-15T12:12:04.924000"
        },
        {
            "utterance_id": 4,
            "interlocutor_id": "BA",
            "text": "プリンターとか",
            "timestamp": "2022-08-15T12:12:19.233000"
        },
        {
            "utterance_id": 5,
            "interlocutor_id": "AK",
            "text": "詳しくはないですが、どうしました？",
            "timestamp": "2022-08-15T12:12:29.405000"
        },
        {
            "utterance_id": 6,
            "interlocutor_id": "BA",
            "text": "なんか、なかのＣＤＲ用の板？が出てきちゃってもとに戻らなくて",
            "timestamp": "2022-08-15T12:12:51.579000"
        },
        {
            "utterance_id": 7,
            "interlocutor_id": "AK",
            "text": "え、そんなことあるんですか。",
            "timestamp": "2022-08-15T12:13:05.666000"
        },
        {
            "utterance_id": 8,
            "interlocutor_id": "BA",
            "text": "なんですよ、なんでだろう",
            "timestamp": "2022-08-15T12:13:11.045000"
        },
        {
            "utterance_id": 9,
            "interlocutor_id": "AK",
            "text": "落としたとかですか？",
            "timestamp": "2022-08-15T12:13:17.562000"
        },
        {
            "utterance_id": 10,
            "interlocutor_id": "BA",
            "text": "落としてないんですけどね",
            "timestamp": "2022-08-15T12:13:33.996000"
        },
        {
            "utterance_id": 11,
            "interlocutor_id": "AK",
            "text": "え、急に出てきたんですか？",
            "timestamp": "2022-08-15T12:13:44.860000"
        },
        {
            "utterance_id": 12,
            "interlocutor_id": "BA",
            "text": "そうなんですよ、なんでだろう",
            "timestamp": "2022-08-15T12:13:55.687000"
        },
        {
            "utterance_id": 13,
            "interlocutor_id": "AK",
            "text": "え、なんか怖いですね。なんでだ。",
            "timestamp": "2022-08-15T12:14:07.560000"
        },
        {
            "utterance_id": 14,
            "interlocutor_id": "BA",
            "text": "ネットで調べてみます",
            "timestamp": "2022-08-15T12:14:20.690000"
        },
        {
            "utterance_id": 15,
            "interlocutor_id": "AK",
            "text": "たしかに。ネットになら何でも答えがのってますよね。",
            "timestamp": "2022-08-15T12:14:34.321000"
        },
        {
            "utterance_id": 16,
            "interlocutor_id": "BA",
            "text": "ですね",
            "timestamp": "2022-08-15T12:14:35.943000"
        },
        {
            "utterance_id": 17,
            "interlocutor_id": "AK",
            "text": "正解を見つけるのに時間はかかりますが。",
            "timestamp": "2022-08-15T12:14:49.428000"
        },
        {
            "utterance_id": 18,
            "interlocutor_id": "BA",
            "text": "でも便利な世の中",
            "timestamp": "2022-08-15T12:14:59.595000"
        },
        {
            "utterance_id": 19,
            "interlocutor_id": "AK",
            "text": "たしかに。ネットなしでは生きられないですね。",
            "timestamp": "2022-08-15T12:15:13.298000"
        },
        {
            "utterance_id": 20,
            "interlocutor_id": "BA",
            "text": "ネットなしでどうやっていきてたんだろう",
            "timestamp": "2022-08-15T12:15:24.831000"
        },
        {
            "utterance_id": 21,
            "interlocutor_id": "AK",
            "text": "人に聞くとかですかね。",
            "timestamp": "2022-08-15T12:15:33.580000"
        },
        {
            "utterance_id": 22,
            "interlocutor_id": "BA",
            "text": "大変だ",
            "timestamp": "2022-08-15T12:15:46.155000"
        },
        {
            "utterance_id": 23,
            "interlocutor_id": "AK",
            "text": "周りに知識が豊富な人がいればいいですけどね。",
            "timestamp": "2022-08-15T12:15:59.641000"
        },
        {
            "utterance_id": 24,
            "interlocutor_id": "BA",
            "text": "本当ですよね",
            "timestamp": "2022-08-15T12:16:08.299000"
        },
        {
            "utterance_id": 25,
            "interlocutor_id": "AK",
            "text": "うちの夫は知ってることでも教えてくれないですよ。",
            "timestamp": "2022-08-15T12:16:21.848000"
        },
        {
            "utterance_id": 26,
            "interlocutor_id": "BA",
            "text": "えーーなんで？",
            "timestamp": "2022-08-15T12:16:27.585000"
        },
        {
            "utterance_id": 27,
            "interlocutor_id": "AK",
            "text": "考える力を身につけろと。",
            "timestamp": "2022-08-15T12:16:40.409000"
        },
        {
            "utterance_id": 28,
            "interlocutor_id": "BA",
            "text": "なるほど",
            "timestamp": "2022-08-15T12:16:45.676000"
        },
        {
            "utterance_id": 29,
            "interlocutor_id": "AK",
            "text": "厳しいです。",
            "timestamp": "2022-08-15T12:16:50.935000"
        }
    ],
    "evaluations": [
        {
            "interlocutor_id": "BA",
            "informativeness": 5,
            "comprehension": 5,
            "familiarity": 5,
            "interest": 5,
            "proactiveness": 5,
            "satisfaction": 5
        },
        {
            "interlocutor_id": "AK",
            "informativeness": 4,
            "comprehension": 5,
            "familiarity": 4,
            "interest": 4,
            "proactiveness": 4,
            "satisfaction": 4
        }
    ]
}