{
    "dialogue_id": 3376,
    "interlocutors": [
        "DK",
        "CY"
    ],
    "utterances": [
        {
            "utterance_id": 0,
            "interlocutor_id": "DK",
            "text": "こんにちはー　よろしくお願いします！",
            "timestamp": "2022-08-28T16:00:21.969000"
        },
        {
            "utterance_id": 1,
            "interlocutor_id": "CY",
            "text": "よろしくお願いします。",
            "timestamp": "2022-08-28T16:00:27.616000"
        },
        {
            "utterance_id": 2,
            "interlocutor_id": "DK",
            "text": "日曜日はお休みですか？",
            "timestamp": "2022-08-28T16:00:50.919000"
        },
        {
            "utterance_id": 3,
            "interlocutor_id": "CY",
            "text": "はい、お休みです。",
            "timestamp": "2022-08-28T16:00:57.719000"
        },
        {
            "utterance_id": 4,
            "interlocutor_id": "DK",
            "text": "私もです　今日は何をされてました？",
            "timestamp": "2022-08-28T16:01:12.961000"
        },
        {
            "utterance_id": 5,
            "interlocutor_id": "CY",
            "text": "今日はバイト探しをしていました。",
            "timestamp": "2022-08-28T16:01:26.106000"
        },
        {
            "utterance_id": 6,
            "interlocutor_id": "DK",
            "text": "そうなんですか　今はコロナの影響で飲食業などが人手不足と聞きますが、どうなんでしょうか？",
            "timestamp": "2022-08-28T16:01:55.678000"
        },
        {
            "utterance_id": 7,
            "interlocutor_id": "CY",
            "text": "そうですね。今までバイトしていたお土産屋さんが閉店してしまって。",
            "timestamp": "2022-08-28T16:02:18.149000"
        },
        {
            "utterance_id": 8,
            "interlocutor_id": "DK",
            "text": "観光業は影響大きく受けましたからね　一度辞めた人が戻ってこないとか",
            "timestamp": "2022-08-28T16:02:55.124000"
        },
        {
            "utterance_id": 9,
            "interlocutor_id": "CY",
            "text": "そうみたいです。外国の方が来られないだけで大きく違うようです。",
            "timestamp": "2022-08-28T16:03:12.452000"
        },
        {
            "utterance_id": 10,
            "interlocutor_id": "DK",
            "text": "また旅行客が来なくなって、解雇されちゃうかもしれませんしねぇ",
            "timestamp": "2022-08-28T16:03:54.225000"
        },
        {
            "utterance_id": 11,
            "interlocutor_id": "CY",
            "text": "それが怖いですよね。飲食店も客が来ないとシフト入れてもらえませんし。",
            "timestamp": "2022-08-28T16:04:17.585000"
        },
        {
            "utterance_id": 12,
            "interlocutor_id": "DK",
            "text": "あと、アルバイトの人がコロナに感染した時が一番たいへんらしいですね",
            "timestamp": "2022-08-28T16:04:55.929000"
        },
        {
            "utterance_id": 13,
            "interlocutor_id": "CY",
            "text": "うんうん！その時って店も閉めないといけないんですかね？",
            "timestamp": "2022-08-28T16:05:27.859000"
        },
        {
            "utterance_id": 14,
            "interlocutor_id": "DK",
            "text": "人が足りないと閉めるしかなくなりますね　実際、バスが運行減らしたりしてましたし",
            "timestamp": "2022-08-28T16:06:05.080000"
        },
        {
            "utterance_id": 15,
            "interlocutor_id": "CY",
            "text": "ですよね。バスの運行減少は田舎民には死活問題です。",
            "timestamp": "2022-08-28T16:06:31.523000"
        },
        {
            "utterance_id": 16,
            "interlocutor_id": "DK",
            "text": "わかります　私の近くのバスも1時間に1本から3本ですから",
            "timestamp": "2022-08-28T16:07:10.214000"
        },
        {
            "utterance_id": 17,
            "interlocutor_id": "CY",
            "text": "こっちもそんな感じです。一本逃すとその後の予定が大きく変わってしまいます。",
            "timestamp": "2022-08-28T16:07:39.641000"
        },
        {
            "utterance_id": 18,
            "interlocutor_id": "DK",
            "text": "かといって、かなり早くから停留所で待つのも嫌ですよね　暑いし",
            "timestamp": "2022-08-28T16:08:08.077000"
        },
        {
            "utterance_id": 19,
            "interlocutor_id": "CY",
            "text": "暑い時期は本当に嫌ですよね。時間はきちんと正しく運行されていますか？",
            "timestamp": "2022-08-28T16:08:38.030000"
        },
        {
            "utterance_id": 20,
            "interlocutor_id": "DK",
            "text": "いや、よく遅れます　道が狭いところを走ってる路線なので",
            "timestamp": "2022-08-28T16:09:09.668000"
        },
        {
            "utterance_id": 21,
            "interlocutor_id": "CY",
            "text": "そうなんですね。こちらも10分や20分遅れはふつうにあります",
            "timestamp": "2022-08-28T16:09:38.096000"
        },
        {
            "utterance_id": 22,
            "interlocutor_id": "DK",
            "text": "それは大変ですね！自分が乗り遅れたのかと思ってしまいそう",
            "timestamp": "2022-08-28T16:10:04.533000"
        },
        {
            "utterance_id": 23,
            "interlocutor_id": "CY",
            "text": "分かります！その後電車に乗ろうとしている時は絶望です。",
            "timestamp": "2022-08-28T16:10:28.273000"
        },
        {
            "utterance_id": 24,
            "interlocutor_id": "DK",
            "text": "そうですよねー　全てが狂ってしまいます",
            "timestamp": "2022-08-28T16:10:57.998000"
        },
        {
            "utterance_id": 25,
            "interlocutor_id": "CY",
            "text": "電車も少ないので1時間くらい空白ができてしまいますね。",
            "timestamp": "2022-08-28T16:11:19.343000"
        },
        {
            "utterance_id": 26,
            "interlocutor_id": "DK",
            "text": "駅の手前で踏切渋滞で遅れて、ここで降ろしてくれってなったことあります",
            "timestamp": "2022-08-28T16:11:55.004000"
        },
        {
            "utterance_id": 27,
            "interlocutor_id": "CY",
            "text": "それは辛い！目的地が見えているところで止まるのが一番やきもきしますね。",
            "timestamp": "2022-08-28T16:12:21.894000"
        },
        {
            "utterance_id": 28,
            "interlocutor_id": "DK",
            "text": "はい　朝に遭遇したのでほんとヤキモキしました！",
            "timestamp": "2022-08-28T16:13:21.356000"
        },
        {
            "utterance_id": 29,
            "interlocutor_id": "CY",
            "text": "朝は特に急いでいるので大変ですよね。",
            "timestamp": "2022-08-28T16:13:34.127000"
        }
    ],
    "evaluations": [
        {
            "interlocutor_id": "DK",
            "informativeness": 5,
            "comprehension": 4,
            "familiarity": 4,
            "interest": 4,
            "proactiveness": 4,
            "satisfaction": 4
        },
        {
            "interlocutor_id": "CY",
            "informativeness": 5,
            "comprehension": 5,
            "familiarity": 5,
            "interest": 5,
            "proactiveness": 5,
            "satisfaction": 5
        }
    ]
}