{
    "dialogue_id": 4221,
    "interlocutors": [
        "DU",
        "BY"
    ],
    "utterances": [
        {
            "utterance_id": 0,
            "interlocutor_id": "DU",
            "text": "こんばんは。",
            "timestamp": "2022-09-12T21:56:30.184000"
        },
        {
            "utterance_id": 1,
            "interlocutor_id": "BY",
            "text": "こんばんは。",
            "timestamp": "2022-09-12T21:56:35.720000"
        },
        {
            "utterance_id": 2,
            "interlocutor_id": "DU",
            "text": "いつも美容室ってカットでいくらくらいしていますか？",
            "timestamp": "2022-09-12T21:56:56.840000"
        },
        {
            "utterance_id": 3,
            "interlocutor_id": "BY",
            "text": "値段ですか？4000円か5000円くらいです。",
            "timestamp": "2022-09-12T21:57:15.402000"
        },
        {
            "utterance_id": 4,
            "interlocutor_id": "DU",
            "text": "私は普段3000円位の所に行ってたんですけど、気になっているところが9000円するんですよね。",
            "timestamp": "2022-09-12T21:57:44.774000"
        },
        {
            "utterance_id": 5,
            "interlocutor_id": "BY",
            "text": "それはかなりお高いですね！何か特別なことがあるんですか？",
            "timestamp": "2022-09-12T21:58:01.853000"
        },
        {
            "utterance_id": 6,
            "interlocutor_id": "DU",
            "text": "ニューヨークドライカットという技法を使って彫刻作品の様にカットしてくれるんです。",
            "timestamp": "2022-09-12T21:58:29.773000"
        },
        {
            "utterance_id": 7,
            "interlocutor_id": "BY",
            "text": "へええ。初めて聞きました。想像できないですが、新しい技術なのでしょうか。",
            "timestamp": "2022-09-12T21:58:58.743000"
        },
        {
            "utterance_id": 8,
            "interlocutor_id": "DU",
            "text": "結構昔からあるけど、大変だからなかなか日本では流行らないようです。",
            "timestamp": "2022-09-12T21:59:19.118000"
        },
        {
            "utterance_id": 9,
            "interlocutor_id": "BY",
            "text": "そうなんですね。どのあたりが大変なんですか。",
            "timestamp": "2022-09-12T21:59:44.752000"
        },
        {
            "utterance_id": 10,
            "interlocutor_id": "DU",
            "text": "すきばさみをつかわず１本１本ハサミで切るので、カットだけで２時間位かかります。",
            "timestamp": "2022-09-12T22:00:10.022000"
        },
        {
            "utterance_id": 11,
            "interlocutor_id": "BY",
            "text": "ええ？一本ずつですか？それは想像外の切り方です。",
            "timestamp": "2022-09-12T22:00:36.289000"
        },
        {
            "utterance_id": 12,
            "interlocutor_id": "DU",
            "text": "何本かまとめて切ったりもしてると思いますが、カットモデルで切ってもらったら出来は凄く良かったんです。",
            "timestamp": "2022-09-12T22:01:06.875000"
        },
        {
            "utterance_id": 13,
            "interlocutor_id": "BY",
            "text": "そうでしたか。一度すごく良い仕上がりになると、またそこで切ってもらいたいですよね。",
            "timestamp": "2022-09-12T22:01:43.350000"
        },
        {
            "utterance_id": 14,
            "interlocutor_id": "DU",
            "text": "その技法を広めたくて１回目は無料でカットしてるようで。インスタで誘われていきました。",
            "timestamp": "2022-09-12T22:02:14.524000"
        },
        {
            "utterance_id": 15,
            "interlocutor_id": "BY",
            "text": "なるほど、今時ですね。でも2時間くらいかかって9000円だったら、結構お安い設定な気がします。",
            "timestamp": "2022-09-12T22:02:44.961000"
        },
        {
            "utterance_id": 16,
            "interlocutor_id": "DU",
            "text": "そうですよね。夫も10年位一緒にいて一番いい仕上がりだったと言ってました。",
            "timestamp": "2022-09-12T22:03:14.188000"
        },
        {
            "utterance_id": 17,
            "interlocutor_id": "BY",
            "text": "それはもう、お墨付きですね。美容院に行く頻度が今度は気になります。",
            "timestamp": "2022-09-12T22:03:41.522000"
        },
        {
            "utterance_id": 18,
            "interlocutor_id": "DU",
            "text": "前回６月で今そろそろ行こうかなって感じなので長持ちはしている気がします。",
            "timestamp": "2022-09-12T22:04:08.777000"
        },
        {
            "utterance_id": 19,
            "interlocutor_id": "BY",
            "text": "3か月だと、かなり長持ちですね。たいていもっと早く形がまとまりにくくなりますから。",
            "timestamp": "2022-09-12T22:04:39.196000"
        },
        {
            "utterance_id": 20,
            "interlocutor_id": "DU",
            "text": "マメな人は月１位で行きますよね。私ずぼらでして。",
            "timestamp": "2022-09-12T22:04:57.197000"
        },
        {
            "utterance_id": 21,
            "interlocutor_id": "BY",
            "text": "私もずぼらです。でも放っておくと行かなくなるので、予約だけは入れて帰ります。",
            "timestamp": "2022-09-12T22:05:17.908000"
        },
        {
            "utterance_id": 22,
            "interlocutor_id": "DU",
            "text": "偉いですね。私先の予約とか入れたら嫌になるタイプなので気が向いてから予約派です。",
            "timestamp": "2022-09-12T22:05:45.709000"
        },
        {
            "utterance_id": 23,
            "interlocutor_id": "BY",
            "text": "一度入れなくて、1年以上行かなかったことがあったので、大いに反省したんです。",
            "timestamp": "2022-09-12T22:06:05.124000"
        },
        {
            "utterance_id": 24,
            "interlocutor_id": "DU",
            "text": "それは凄いですね。前髪とか大丈夫でしたか？",
            "timestamp": "2022-09-12T22:06:22.026000"
        },
        {
            "utterance_id": 25,
            "interlocutor_id": "BY",
            "text": "前髪を作っていなかったので、全く問題なくって。気づいたらすごく伸びていました。",
            "timestamp": "2022-09-12T22:06:45.726000"
        },
        {
            "utterance_id": 26,
            "interlocutor_id": "DU",
            "text": "作らないとそんな利点があるのですね。",
            "timestamp": "2022-09-12T22:07:00.238000"
        },
        {
            "utterance_id": 27,
            "interlocutor_id": "BY",
            "text": "そうなんです。でもやっぱり傷みも出てくるので、それなりに行かないとな、と。",
            "timestamp": "2022-09-12T22:07:30.253000"
        },
        {
            "utterance_id": 28,
            "interlocutor_id": "DU",
            "text": "身だしなみって大事ですものね。私もそろそろどうするか決めます。",
            "timestamp": "2022-09-12T22:07:59.658000"
        },
        {
            "utterance_id": 29,
            "interlocutor_id": "BY",
            "text": "そうなんです。意外に髪って見られますね。またどうなったか聞かせてください。",
            "timestamp": "2022-09-12T22:08:22.261000"
        }
    ],
    "evaluations": [
        {
            "interlocutor_id": "DU",
            "informativeness": 5,
            "comprehension": 5,
            "familiarity": 5,
            "interest": 5,
            "proactiveness": 5,
            "satisfaction": 5
        },
        {
            "interlocutor_id": "BY",
            "informativeness": 4,
            "comprehension": 5,
            "familiarity": 5,
            "interest": 4,
            "proactiveness": 5,
            "satisfaction": 4
        }
    ]
}