{
    "dialogue_id": 6043,
    "interlocutors": [
        "HE",
        "GW"
    ],
    "utterances": [
        {
            "utterance_id": 0,
            "interlocutor_id": "HE",
            "text": "こんにちは！",
            "timestamp": "2022-10-02T15:13:02.341000"
        },
        {
            "utterance_id": 1,
            "interlocutor_id": "GW",
            "text": "こんにちは！",
            "timestamp": "2022-10-02T15:13:05.730000"
        },
        {
            "utterance_id": 2,
            "interlocutor_id": "HE",
            "text": "まだカフェいますか？",
            "timestamp": "2022-10-02T15:13:11.765000"
        },
        {
            "utterance_id": 3,
            "interlocutor_id": "GW",
            "text": "まだ作業してますね",
            "timestamp": "2022-10-02T15:13:18.107000"
        },
        {
            "utterance_id": 4,
            "interlocutor_id": "HE",
            "text": "おつかれさまです！",
            "timestamp": "2022-10-02T15:13:22.259000"
        },
        {
            "utterance_id": 5,
            "interlocutor_id": "GW",
            "text": "こんできました",
            "timestamp": "2022-10-02T15:13:28.785000"
        },
        {
            "utterance_id": 6,
            "interlocutor_id": "HE",
            "text": "だいぶですか？",
            "timestamp": "2022-10-02T15:13:31.849000"
        },
        {
            "utterance_id": 7,
            "interlocutor_id": "GW",
            "text": "ほぼ満席です",
            "timestamp": "2022-10-02T15:13:35.752000"
        },
        {
            "utterance_id": 8,
            "interlocutor_id": "HE",
            "text": "それきついでｓね",
            "timestamp": "2022-10-02T15:13:40.342000"
        },
        {
            "utterance_id": 9,
            "interlocutor_id": "GW",
            "text": "時間帯ですかね",
            "timestamp": "2022-10-02T15:13:44.098000"
        },
        {
            "utterance_id": 10,
            "interlocutor_id": "HE",
            "text": "それもありそうです",
            "timestamp": "2022-10-02T15:13:50.109000"
        },
        {
            "utterance_id": 11,
            "interlocutor_id": "GW",
            "text": "お昼後ですもんね",
            "timestamp": "2022-10-02T15:13:58.693000"
        },
        {
            "utterance_id": 12,
            "interlocutor_id": "HE",
            "text": "作業してる人多いです",
            "timestamp": "2022-10-02T15:14:04.165000"
        },
        {
            "utterance_id": 13,
            "interlocutor_id": "GW",
            "text": "お仲間ですね",
            "timestamp": "2022-10-02T15:14:09.105000"
        },
        {
            "utterance_id": 14,
            "interlocutor_id": "HE",
            "text": "ですです",
            "timestamp": "2022-10-02T15:14:14.203000"
        },
        {
            "utterance_id": 15,
            "interlocutor_id": "GW",
            "text": "広いとこですか",
            "timestamp": "2022-10-02T15:14:19.533000"
        },
        {
            "utterance_id": 16,
            "interlocutor_id": "HE",
            "text": "かなりひろいです",
            "timestamp": "2022-10-02T15:14:26.268000"
        },
        {
            "utterance_id": 17,
            "interlocutor_id": "GW",
            "text": "チェーンですか？",
            "timestamp": "2022-10-02T15:14:31.504000"
        },
        {
            "utterance_id": 18,
            "interlocutor_id": "HE",
            "text": "たぶん？",
            "timestamp": "2022-10-02T15:14:35.631000"
        },
        {
            "utterance_id": 19,
            "interlocutor_id": "GW",
            "text": "有名店ではないんですか",
            "timestamp": "2022-10-02T15:14:42.934000"
        },
        {
            "utterance_id": 20,
            "interlocutor_id": "HE",
            "text": "数店舗くらいです",
            "timestamp": "2022-10-02T15:14:50.237000"
        },
        {
            "utterance_id": 21,
            "interlocutor_id": "GW",
            "text": "おお、でもいいですね",
            "timestamp": "2022-10-02T15:14:57.284000"
        },
        {
            "utterance_id": 22,
            "interlocutor_id": "HE",
            "text": "広いしおいしいです",
            "timestamp": "2022-10-02T15:15:03.747000"
        },
        {
            "utterance_id": 23,
            "interlocutor_id": "GW",
            "text": "フードですか？",
            "timestamp": "2022-10-02T15:15:09.331000"
        },
        {
            "utterance_id": 24,
            "interlocutor_id": "HE",
            "text": "ドリンクです",
            "timestamp": "2022-10-02T15:15:18.826000"
        },
        {
            "utterance_id": 25,
            "interlocutor_id": "GW",
            "text": "それだいじですよね",
            "timestamp": "2022-10-02T15:15:22.878000"
        },
        {
            "utterance_id": 26,
            "interlocutor_id": "HE",
            "text": "いちばんだいじです",
            "timestamp": "2022-10-02T15:15:26.972000"
        },
        {
            "utterance_id": 27,
            "interlocutor_id": "GW",
            "text": "効率変わりそう",
            "timestamp": "2022-10-02T15:15:31.735000"
        },
        {
            "utterance_id": 28,
            "interlocutor_id": "HE",
            "text": "かわりますよ！",
            "timestamp": "2022-10-02T15:15:35.431000"
        },
        {
            "utterance_id": 29,
            "interlocutor_id": "GW",
            "text": "ですよね！",
            "timestamp": "2022-10-02T15:15:38.513000"
        }
    ],
    "evaluations": [
        {
            "interlocutor_id": "HE",
            "informativeness": 5,
            "comprehension": 5,
            "familiarity": 5,
            "interest": 5,
            "proactiveness": 5,
            "satisfaction": 5
        },
        {
            "interlocutor_id": "GW",
            "informativeness": 5,
            "comprehension": 5,
            "familiarity": 5,
            "interest": 5,
            "proactiveness": 5,
            "satisfaction": 5
        }
    ]
}