{
    "dialogue_id": 6152,
    "interlocutors": [
        "AR",
        "HL"
    ],
    "utterances": [
        {
            "utterance_id": 0,
            "interlocutor_id": "AR",
            "text": "はじめまして",
            "timestamp": "2022-10-03T10:27:22.555000"
        },
        {
            "utterance_id": 1,
            "interlocutor_id": "HL",
            "text": "はじめまして。",
            "timestamp": "2022-10-03T10:27:31.800000"
        },
        {
            "utterance_id": 2,
            "interlocutor_id": "AR",
            "text": "今日はお休みですか。",
            "timestamp": "2022-10-03T10:27:41.579000"
        },
        {
            "utterance_id": 3,
            "interlocutor_id": "HL",
            "text": "はい。お休みです。",
            "timestamp": "2022-10-03T10:27:54.988000"
        },
        {
            "utterance_id": 4,
            "interlocutor_id": "AR",
            "text": "普段はパートか何かを？",
            "timestamp": "2022-10-03T10:28:09.417000"
        },
        {
            "utterance_id": 5,
            "interlocutor_id": "HL",
            "text": "たまに実家の仕事を手伝っています。",
            "timestamp": "2022-10-03T10:28:27.319000"
        },
        {
            "utterance_id": 6,
            "interlocutor_id": "AR",
            "text": "自営業なんですね。",
            "timestamp": "2022-10-03T10:28:40.337000"
        },
        {
            "utterance_id": 7,
            "interlocutor_id": "HL",
            "text": "実家がですね。主人はサラリーマンです。",
            "timestamp": "2022-10-03T10:29:11.359000"
        },
        {
            "utterance_id": 8,
            "interlocutor_id": "AR",
            "text": "先日のシルバーウィークにはどちらかに行かれましたか？",
            "timestamp": "2022-10-03T10:29:41.785000"
        },
        {
            "utterance_id": 9,
            "interlocutor_id": "HL",
            "text": "ちょうど台風がきまして、どこへも行ってません。",
            "timestamp": "2022-10-03T10:30:17.806000"
        },
        {
            "utterance_id": 10,
            "interlocutor_id": "AR",
            "text": "あーそうでしたよね。私キャンプ行ってびしょびしょになったんでした、あはは。",
            "timestamp": "2022-10-03T10:30:41.466000"
        },
        {
            "utterance_id": 11,
            "interlocutor_id": "HL",
            "text": "キャンプ好きなんですか？",
            "timestamp": "2022-10-03T10:30:56.942000"
        },
        {
            "utterance_id": 12,
            "interlocutor_id": "AR",
            "text": "好きですよ、コロナになってから特によくいくようになりました！",
            "timestamp": "2022-10-03T10:31:33.941000"
        },
        {
            "utterance_id": 13,
            "interlocutor_id": "HL",
            "text": "そうなんですね。おひとりで？それとも家族とかと？",
            "timestamp": "2022-10-03T10:32:11.727000"
        },
        {
            "utterance_id": 14,
            "interlocutor_id": "AR",
            "text": "家族と行きます。実家もキャンプ好きなので大勢で行きます。",
            "timestamp": "2022-10-03T10:32:34.910000"
        },
        {
            "utterance_id": 15,
            "interlocutor_id": "HL",
            "text": "それは楽しそうですね！近場に行くのですか？",
            "timestamp": "2022-10-03T10:33:19.049000"
        },
        {
            "utterance_id": 16,
            "interlocutor_id": "AR",
            "text": "私は茨城に住んでいるのですが、那須によく行きます。車で２時間くらいです。",
            "timestamp": "2022-10-03T10:33:48.249000"
        },
        {
            "utterance_id": 17,
            "interlocutor_id": "HL",
            "text": "２時間ならちょっとしたドライブ感も楽しめますね。",
            "timestamp": "2022-10-03T10:34:22.816000"
        },
        {
            "utterance_id": 18,
            "interlocutor_id": "AR",
            "text": "そうなんですよ、途中道の駅に寄るのも楽しみです。",
            "timestamp": "2022-10-03T10:34:56.996000"
        },
        {
            "utterance_id": 19,
            "interlocutor_id": "HL",
            "text": "キャンプの材料も買えますね。",
            "timestamp": "2022-10-03T10:35:14.710000"
        },
        {
            "utterance_id": 20,
            "interlocutor_id": "AR",
            "text": "はい、だいたい、道の駅で野菜カレーやシチュー、BBQの材料にしています。",
            "timestamp": "2022-10-03T10:36:17.506000"
        },
        {
            "utterance_id": 21,
            "interlocutor_id": "HL",
            "text": "新鮮な食材で最高ですね！あなたがお料理するのですか？",
            "timestamp": "2022-10-03T10:36:50.101000"
        },
        {
            "utterance_id": 22,
            "interlocutor_id": "AR",
            "text": "子供用包丁も持って行って、みんなでやるようにしています！",
            "timestamp": "2022-10-03T10:37:39.364000"
        },
        {
            "utterance_id": 23,
            "interlocutor_id": "HL",
            "text": "楽しそう！キャンプに興味があるのですが、なかなか準備が大変そうでしていません。",
            "timestamp": "2022-10-03T10:38:37.739000"
        },
        {
            "utterance_id": 24,
            "interlocutor_id": "AR",
            "text": "たしかに準備は大変ですよね。１回目ともなると、テントやテーブル椅子など一式そろえないといけませんしね。",
            "timestamp": "2022-10-03T10:39:27.211000"
        },
        {
            "utterance_id": 25,
            "interlocutor_id": "HL",
            "text": "そうなんです。ホームセンターとかでキャンプ用品をチラチラ見てるんですけどね。",
            "timestamp": "2022-10-03T10:40:23.764000"
        },
        {
            "utterance_id": 26,
            "interlocutor_id": "AR",
            "text": "けど、昔に比べると価格はだいぶ手ごろになったと思います。",
            "timestamp": "2022-10-03T10:41:04.714000"
        },
        {
            "utterance_id": 27,
            "interlocutor_id": "HL",
            "text": "そうですね。子供たちのためにも行ってみるかな。",
            "timestamp": "2022-10-03T10:41:50.705000"
        },
        {
            "utterance_id": 28,
            "interlocutor_id": "AR",
            "text": "自然の中でぼーっとするのは、大人にとっても大事かもしれません。",
            "timestamp": "2022-10-03T10:42:21.084000"
        },
        {
            "utterance_id": 29,
            "interlocutor_id": "HL",
            "text": "そうですね。ありがとうございました。",
            "timestamp": "2022-10-03T10:42:36.257000"
        }
    ],
    "evaluations": [
        {
            "interlocutor_id": "AR",
            "informativeness": 5,
            "comprehension": 5,
            "familiarity": 5,
            "interest": 5,
            "proactiveness": 5,
            "satisfaction": 5
        },
        {
            "interlocutor_id": "HL",
            "informativeness": 5,
            "comprehension": 5,
            "familiarity": 5,
            "interest": 5,
            "proactiveness": 5,
            "satisfaction": 5
        }
    ]
}