{
    "dialogue_id": 9384,
    "interlocutors": [
        "BA",
        "AI"
    ],
    "utterances": [
        {
            "utterance_id": 0,
            "interlocutor_id": "BA",
            "text": "宜しくお願いします",
            "timestamp": "2022-08-08T09:21:53.427000"
        },
        {
            "utterance_id": 1,
            "interlocutor_id": "AI",
            "text": "よろしくお願いします",
            "timestamp": "2022-08-08T09:21:58.474000"
        },
        {
            "utterance_id": 2,
            "interlocutor_id": "BA",
            "text": "最近嬉しかったことは？",
            "timestamp": "2022-08-08T09:22:10.958000"
        },
        {
            "utterance_id": 3,
            "interlocutor_id": "AI",
            "text": "おお、なんだろう、チョイ考え中",
            "timestamp": "2022-08-08T09:22:22.665000"
        },
        {
            "utterance_id": 4,
            "interlocutor_id": "BA",
            "text": "すぐ出ないですよね",
            "timestamp": "2022-08-08T09:22:33.186000"
        },
        {
            "utterance_id": 5,
            "interlocutor_id": "AI",
            "text": "そうだなあ、うれしいって難しいなあ",
            "timestamp": "2022-08-08T09:22:45.127000"
        },
        {
            "utterance_id": 6,
            "interlocutor_id": "BA",
            "text": "自分で聞いて、難しいなって思いました",
            "timestamp": "2022-08-08T09:22:56.407000"
        },
        {
            "utterance_id": 7,
            "interlocutor_id": "AI",
            "text": "あ、ツイッターで間違って結構バズったことかも",
            "timestamp": "2022-08-08T09:23:08.314000"
        },
        {
            "utterance_id": 8,
            "interlocutor_id": "BA",
            "text": "え！なんですか",
            "timestamp": "2022-08-08T09:23:21.659000"
        },
        {
            "utterance_id": 9,
            "interlocutor_id": "AI",
            "text": "なんか家のピアノの写真あげたら、３０００いいね超えた",
            "timestamp": "2022-08-08T09:23:36.426000"
        },
        {
            "utterance_id": 10,
            "interlocutor_id": "BA",
            "text": "すごい！まちがって、って？",
            "timestamp": "2022-08-08T09:23:54.551000"
        },
        {
            "utterance_id": 11,
            "interlocutor_id": "AI",
            "text": "はい、なんかの間違いですよね、３０００いいねも超えるなんて",
            "timestamp": "2022-08-08T09:24:08.973000"
        },
        {
            "utterance_id": 12,
            "interlocutor_id": "BA",
            "text": "あ、そういうことか、",
            "timestamp": "2022-08-08T09:24:18.587000"
        },
        {
            "utterance_id": 13,
            "interlocutor_id": "AI",
            "text": "楽譜を上から物干しのように洗濯ばさみでつるしてるんですが",
            "timestamp": "2022-08-08T09:24:35.871000"
        },
        {
            "utterance_id": 14,
            "interlocutor_id": "BA",
            "text": "おもしろい",
            "timestamp": "2022-08-08T09:24:43.752000"
        },
        {
            "utterance_id": 15,
            "interlocutor_id": "AI",
            "text": "私究極のめんどくさがりで、譜めくりが面倒だなと",
            "timestamp": "2022-08-08T09:24:58.612000"
        },
        {
            "utterance_id": 16,
            "interlocutor_id": "BA",
            "text": "それがいいねの理由かな！？",
            "timestamp": "2022-08-08T09:25:11.224000"
        },
        {
            "utterance_id": 17,
            "interlocutor_id": "AI",
            "text": "はい、その写真あげたらむちゃくちゃいいねつきました",
            "timestamp": "2022-08-08T09:25:19.928000"
        },
        {
            "utterance_id": 18,
            "interlocutor_id": "BA",
            "text": "みんな便利だな！と思ったんですね！",
            "timestamp": "2022-08-08T09:25:30.488000"
        },
        {
            "utterance_id": 19,
            "interlocutor_id": "AI",
            "text": "いや、ありえんわとか、そんなのばっかでしたが",
            "timestamp": "2022-08-08T09:25:42.320000"
        },
        {
            "utterance_id": 20,
            "interlocutor_id": "BA",
            "text": "え！そうなのか",
            "timestamp": "2022-08-08T09:25:54.765000"
        },
        {
            "utterance_id": 21,
            "interlocutor_id": "AI",
            "text": "ただねえ、譜めくり面倒だまでは共感してくれたのかなって",
            "timestamp": "2022-08-08T09:26:07.059000"
        },
        {
            "utterance_id": 22,
            "interlocutor_id": "BA",
            "text": "だといいですね",
            "timestamp": "2022-08-08T09:26:17.900000"
        },
        {
            "utterance_id": 23,
            "interlocutor_id": "AI",
            "text": "ここまでするかとか、暗譜しろとか",
            "timestamp": "2022-08-08T09:26:26.422000"
        },
        {
            "utterance_id": 24,
            "interlocutor_id": "BA",
            "text": "うける",
            "timestamp": "2022-08-08T09:26:34.534000"
        },
        {
            "utterance_id": 25,
            "interlocutor_id": "AI",
            "text": "首いたくなりそうとか",
            "timestamp": "2022-08-08T09:26:42.533000"
        },
        {
            "utterance_id": 26,
            "interlocutor_id": "BA",
            "text": "いろんな意見が",
            "timestamp": "2022-08-08T09:26:50.225000"
        },
        {
            "utterance_id": 27,
            "interlocutor_id": "AI",
            "text": "私にとっては日常なのですがね",
            "timestamp": "2022-08-08T09:26:58.898000"
        },
        {
            "utterance_id": 28,
            "interlocutor_id": "BA",
            "text": "なるほど",
            "timestamp": "2022-08-08T09:27:05.648000"
        },
        {
            "utterance_id": 29,
            "interlocutor_id": "AI",
            "text": "みんなにとっては普通じゃなかったっぽい",
            "timestamp": "2022-08-08T09:27:13.607000"
        }
    ],
    "evaluations": [
        {
            "interlocutor_id": "BA",
            "informativeness": 5,
            "comprehension": 5,
            "familiarity": 5,
            "interest": 5,
            "proactiveness": 5,
            "satisfaction": 5
        },
        {
            "interlocutor_id": "AI",
            "informativeness": 5,
            "comprehension": 5,
            "familiarity": 5,
            "interest": 5,
            "proactiveness": 5,
            "satisfaction": 5
        }
    ]
}