{
    "dialogue_id": 9875,
    "interlocutors": [
        "DY",
        "IK"
    ],
    "utterances": [
        {
            "utterance_id": 0,
            "interlocutor_id": "DY",
            "text": "こんばんは、よろしくお願いします。",
            "timestamp": "2022-08-09T18:05:05.327000"
        },
        {
            "utterance_id": 1,
            "interlocutor_id": "IK",
            "text": "こちらこそ、よろしくお願いします。",
            "timestamp": "2022-08-09T18:05:02.830000"
        },
        {
            "utterance_id": 2,
            "interlocutor_id": "DY",
            "text": "最近した高い買い物ってなにかありますか？",
            "timestamp": "2022-08-09T18:05:14.899000"
        },
        {
            "utterance_id": 3,
            "interlocutor_id": "IK",
            "text": "買い物をした記憶すらないです。何かありますか？",
            "timestamp": "2022-08-09T18:06:25.363000"
        },
        {
            "utterance_id": 4,
            "interlocutor_id": "DY",
            "text": "今月石垣島に行こうと思いましてその飛行機代やら。コロナ流行っててどうするか迷ってるのですが。",
            "timestamp": "2022-08-09T18:07:17.036000"
        },
        {
            "utterance_id": 5,
            "interlocutor_id": "IK",
            "text": "知り合いは、ピーチの格安飛行機で3000円ぐらいで行ったそうです。",
            "timestamp": "2022-08-09T18:08:00.273000"
        },
        {
            "utterance_id": 6,
            "interlocutor_id": "DY",
            "text": "そんな安いんですか！なんか今は繁忙期だからか片道で30000円くらいしました。",
            "timestamp": "2022-08-09T18:08:21.634000"
        },
        {
            "utterance_id": 7,
            "interlocutor_id": "IK",
            "text": "確かに今は繁忙期ですね。それでも3万円は高いですね。",
            "timestamp": "2022-08-09T18:08:56.511000"
        },
        {
            "utterance_id": 8,
            "interlocutor_id": "DY",
            "text": "高いですよね。ホテル代もセットのプランを予約したのですが、かなりの大金を持ってかれました。",
            "timestamp": "2022-08-09T18:09:25.336000"
        },
        {
            "utterance_id": 9,
            "interlocutor_id": "IK",
            "text": "それはバカンスな感じでの旅行ですか？",
            "timestamp": "2022-08-09T18:09:58.895000"
        },
        {
            "utterance_id": 10,
            "interlocutor_id": "DY",
            "text": "実は新婚旅行にまだ行けていなくて、もう国内で行ってしまおうとなった次第です。",
            "timestamp": "2022-08-09T18:10:30.021000"
        },
        {
            "utterance_id": 11,
            "interlocutor_id": "IK",
            "text": "なるほど。そういえば友人は現地で、原付を借りて島を一周したと言っていました。",
            "timestamp": "2022-08-09T18:11:10.762000"
        },
        {
            "utterance_id": 12,
            "interlocutor_id": "DY",
            "text": "なるほど、原付で周るのは気持ちよさそうですね！石垣島は初めてなのですごく楽しみにしています。",
            "timestamp": "2022-08-09T18:11:59.127000"
        },
        {
            "utterance_id": 13,
            "interlocutor_id": "IK",
            "text": "海も綺麗だそうなので、羨ましいです。",
            "timestamp": "2022-08-09T18:12:30.572000"
        },
        {
            "utterance_id": 14,
            "interlocutor_id": "DY",
            "text": "キレイみたいですよね。観光ガイドブックを買ったのですが、写真ですでにきれいでした。",
            "timestamp": "2022-08-09T18:12:56.644000"
        },
        {
            "utterance_id": 15,
            "interlocutor_id": "IK",
            "text": "ダイビングとかはするんですか？",
            "timestamp": "2022-08-09T18:13:11.503000"
        },
        {
            "utterance_id": 16,
            "interlocutor_id": "DY",
            "text": "ダイビングは今回はしない予定です。というのも、妻が泳ぎが苦手みたいで。",
            "timestamp": "2022-08-09T18:13:32.208000"
        },
        {
            "utterance_id": 17,
            "interlocutor_id": "IK",
            "text": "なるほど。無理は禁物ですね。",
            "timestamp": "2022-08-09T18:14:15.489000"
        },
        {
            "utterance_id": 18,
            "interlocutor_id": "DY",
            "text": "そうですね、なにかあったら怖いので。ただ足がつくところでのシュノーケリングはやる予定です。",
            "timestamp": "2022-08-09T18:14:33.790000"
        },
        {
            "utterance_id": 19,
            "interlocutor_id": "IK",
            "text": "海が綺麗なので、絶対楽しいですよ。",
            "timestamp": "2022-08-09T18:14:56.254000"
        },
        {
            "utterance_id": 20,
            "interlocutor_id": "DY",
            "text": "ですよね！潮の満ち引きで数時間しか上陸できない島みたいなのもあるみたいで、とても楽しみです。",
            "timestamp": "2022-08-09T18:15:23.096000"
        },
        {
            "utterance_id": 21,
            "interlocutor_id": "IK",
            "text": "海が透き通るぐらいキレいだと、まるで空を飛んでいるような感じになり、楽しかったです。",
            "timestamp": "2022-08-09T18:16:02.104000"
        },
        {
            "utterance_id": 22,
            "interlocutor_id": "DY",
            "text": "すごいですね、それはどこに行ったときのことですか？",
            "timestamp": "2022-08-09T18:16:18.159000"
        },
        {
            "utterance_id": 23,
            "interlocutor_id": "IK",
            "text": "日本海の国立公園とかはすごく綺麗です。琴吹浜とか。",
            "timestamp": "2022-08-09T18:16:56.170000"
        },
        {
            "utterance_id": 24,
            "interlocutor_id": "DY",
            "text": "日本海側ですか！なるほど。琴吹って何県ですか？",
            "timestamp": "2022-08-09T18:17:25.683000"
        },
        {
            "utterance_id": 25,
            "interlocutor_id": "IK",
            "text": "京都の丹後半島だったと思います。",
            "timestamp": "2022-08-09T18:17:47.307000"
        },
        {
            "utterance_id": 26,
            "interlocutor_id": "DY",
            "text": "京都ですか！あまり海のイメージはなかったのですが、きれいなんですね。",
            "timestamp": "2022-08-09T18:18:10.750000"
        },
        {
            "utterance_id": 27,
            "interlocutor_id": "IK",
            "text": "京都のだいぶ、上の方ですけどね。",
            "timestamp": "2022-08-09T18:18:50.861000"
        },
        {
            "utterance_id": 28,
            "interlocutor_id": "DY",
            "text": "なるほど！今日は話せて楽しかったです、ありがとうございました！",
            "timestamp": "2022-08-09T18:19:14.346000"
        },
        {
            "utterance_id": 29,
            "interlocutor_id": "IK",
            "text": "こちらこそ、ありがとうございました。",
            "timestamp": "2022-08-09T18:19:29.625000"
        }
    ],
    "evaluations": [
        {
            "interlocutor_id": "DY",
            "informativeness": 4,
            "comprehension": 4,
            "familiarity": 3,
            "interest": 3,
            "proactiveness": 4,
            "satisfaction": 3
        },
        {
            "interlocutor_id": "IK",
            "informativeness": 4,
            "comprehension": 4,
            "familiarity": 4,
            "interest": 5,
            "proactiveness": 4,
            "satisfaction": 4
        }
    ]
}